beau_pyrm/__init__.py
beau_pyrm/main.py
beau_pyrm-0.1.3.dist-info/entry_points.txt
beau_pyrm-0.1.3.dist-info/LICENSE
beau_pyrm-0.1.3.dist-info/WHEEL
beau_pyrm-0.1.3.dist-info/METADATA
beau_pyrm-0.1.3.dist-info/RECORD
