Metadata-Version: 2.1
Name: beau-pyrm
Version: 0.1.3
Summary: Very simple relationship manager written in Python.
License: MIT
Author: Beau Hilton
Author-email: beau.hilton@vumc.org
Requires-Python: >=3.9,<4.0
Classifier: License :: OSI Approved :: MIT License
Classifier: Programming Language :: Python :: 3
Classifier: Programming Language :: Python :: 3.9
Requires-Dist: dateparser (>=1.0.0,<2.0.0)
Requires-Dist: pandas (>=1.3.0,<2.0.0)
Requires-Dist: pendulum (>=2.1.2,<3.0.0)
Requires-Dist: rich (>=10.6.0,<11.0.0)
Requires-Dist: typer[all] (>=0.3.2,<0.4.0)
